examples/agent_history_basic.py
examples/agent_tool_usage_benchmark.py
examples/agent_with_mcp_tools.py
examples/agent_with_remote_mcp_sse.py
examples/chat_history_comparison.py
examples/chat_history_display.py
examples/eda.py
examples/hierarchical_structure.py
examples/history_loading.py
examples/history_loading_with_assistant_supervisor.py
examples/multi_argument_function_calling.py
examples/multi_logger.py
examples/multiple_tool_calls.py
examples/output_schema_examples.py
examples/schema_aware_workflow_example.py
examples/tool_usage_terminal.py
examples/workflow_with_custom_id.py
examples/config_mcp_schema/config_mcp_schema.py
examples/memory_task_management/example_memory_management.py
examples/memory_task_management/task_tools.py
examples/single_agent_yaml/test_single_agent_loader.py
examples/supervisor_multi_mcp/add_server.py
examples/supervisor_multi_mcp/example_multi_mcp.py
examples/supervisor_multi_mcp/weather_server.py
examples/task_management_with_yaml/example_task_management.py
examples/task_management_with_yaml/task_tools.py
examples/test_studio_yaml/run.py
src/xronai/__init__.py
src/xronai/config/__init__.py
src/xronai/config/agent_factory.py
src/xronai/config/config_validator.py
src/xronai/config/yaml_config.py
src/xronai/core/__init__.py
src/xronai/core/agents.py
src/xronai/core/ai.py
src/xronai/core/supervisor.py
src/xronai/history/__init__.py
src/xronai/history/history_manager.py
src/xronai/server/main.py
src/xronai/server/ui/app.js
src/xronai/server/ui/index.html
src/xronai/server/ui/style.css
src/xronai/server/ui/assets/favicon.png
src/xronai/server/ui/assets/studio-logo-light.png
src/xronai/server/ui/assets/studio-logo.png
src/xronai/tools/__init__.py
src/xronai/tools/terminal.py
src/xronai/utils/__init__.py
src/xronai/utils/debugger.py
studio/__init__.py
studio/cli.py
studio/server/__init__.py
studio/server/export_utils.py
studio/server/graph_utils.py
studio/server/main.py
studio/server/state.py
studio/server/yaml_to_drawflow.py
xronai-0.2.8.dist-info/licenses/LICENSE
xronai-0.2.8.dist-info/METADATA
xronai-0.2.8.dist-info/WHEEL
xronai-0.2.8.dist-info/entry_points.txt
xronai-0.2.8.dist-info/top_level.txt
xronai-0.2.8.dist-info/RECORD
